changepoint-0.4.0.dist-info/METADATA
changepoint-0.4.0.dist-info/WHEEL
changepoint/__init__.py
changepoint/changepoint.cp310-win_amd64.pyd
changepoint-0.4.0.dist-info/RECORD
