Metadata-Version: 2.4
Name: changepoint
Version: 0.4.0
Classifier: Programming Language :: Python :: 3
Classifier: License :: OSI Approved :: MIT License
Classifier: Operating System :: OS Independent
Classifier: Topic :: Scientific/Engineering :: Mathematics
Requires-Dist: numpy>=1.21.6
Summary: A Bayesian change point library
Keywords: changepoint
Author-email: Redpoll <info@redpoll.ai>
Requires-Python: >=3.7, <4
Project-URL: Repository, https://github.com/promised-ai/changepoint
